nonebot_plugin_authrespond/__init__.py
nonebot_plugin_authrespond/config.py
nonebot_plugin_authrespond/cubp.py
nonebot_plugin_authrespond/perm.py
nonebot_plugin_authrespond/plugins_data.py
nonebot_plugin_authrespond/run.py
nonebot_plugin_authrespond-1.8.dist-info/LICENSE
nonebot_plugin_authrespond-1.8.dist-info/METADATA
nonebot_plugin_authrespond-1.8.dist-info/WHEEL
nonebot_plugin_authrespond-1.8.dist-info/top_level.txt
nonebot_plugin_authrespond-1.8.dist-info/RECORD
