Metadata-Version: 2.1
Name: nonebot-plugin-authrespond
Version: 1.8
Summary: nonebot简单易用的黑名单插件，实现分插件拉黑用户/群聊/全局
Author: cubstaryow
Author-email: cub_staryow@outlook.com
License: GNU GENERAL PUBLIC LICENSE
Project-URL: repository, https://github.com/cubstaryow/nonebot-plugin-authrespond
Keywords: egg,bacon,sausage,tomatoes,Lobster Thermidor
Classifier: Development Status :: 4 - Beta
Classifier: Programming Language :: Python
Requires-Python: >=3.10
License-File: LICENSE
Requires-Dist: nonebot2
Requires-Dist: nonebot-plugin-localstore
Requires-Dist: nonebot-plugin-session
Requires-Dist: nonebot-plugin-alconna
